MANIFEST.in
README.txt
setup.cfg
setup.py
trytond/__init__.py
trytond/modules/__init__.py
trytond/modules/account_nl/__init__.py
trytond/modules/account_nl/__tryton__.py
trytond/modules/account_nl/account_chart_netherlands.xml
trytond/modules/account_nl/account_nl.xml
trytond/modules/account_nl/converter.py
trytond_account_nl.egg-info/PKG-INFO
trytond_account_nl.egg-info/SOURCES.txt
trytond_account_nl.egg-info/dependency_links.txt
trytond_account_nl.egg-info/entry_points.txt
trytond_account_nl.egg-info/namespace_packages.txt
trytond_account_nl.egg-info/not-zip-safe
trytond_account_nl.egg-info/requires.txt
trytond_account_nl.egg-info/top_level.txt