Metadata-Version: 1.0
Name: trytond-account-nl
Version: 2.2.2
Summary: Define an account chart template for The Netherlands.
